{
  "aurick": 3,
  "tenna": 3,
  "remind": 1,
  "humind": 2,
  "shamind": 3,
  "freymind": 3,
  "comind": 4,
  "resona": 4,
  "manyfold": 4,
  "mind of us": 4,
  "office of many": 4,
  "kin": 4,
  "chorus": 4,
  "thrum": 3,
  "kinweave": 3,
  "orbit": 3,
  "kokoro": 4,
  "noos": 4,
  "noomind": 4,
  "koru": 4,
  "vimind": 2,
  "gigabrain": 5,
  "cobrain": 3,
  "whirlmind": 3,
  "livemind": 2,
  "hypermind": 1,
  "eumind": 3,
  "polymind": 3,
  "flaaffemind": 1,
  "maximind": 2,
  "arcmind": 2,
  "neomind": 2,
  "koromi": 4
}